README.md
setup.py
MapDatumTrans/__init__.py
MapDatumTrans/map_datum_trans.py
MapDatumTrans.egg-info/PKG-INFO
MapDatumTrans.egg-info/SOURCES.txt
MapDatumTrans.egg-info/dependency_links.txt
MapDatumTrans.egg-info/top_level.txt