Metadata-Version: 2.1
Name: MapDatumTrans
Version: 1.0.1
Summary: A Transformer for different map datum, include WGS84, GCJ-02, BD-09
Home-page: https://github.com/bluicezhen/MapDatumTrans
Author: Bluice Zhen
Author-email: bluice.zhen@gmail.com
License: MIT
Keywords: WGS84,GCJ-02,BD-09
Platform: UNKNOWN
Classifier: Development Status :: 3 - Alpha
Classifier: Intended Audience :: Developers
Classifier: Topic :: Software Development :: Build Tools
Classifier: License :: OSI Approved :: MIT License
Classifier: Programming Language :: Python :: 3
Classifier: Programming Language :: Python :: 3.6
